{
 "partyTwin": "diplomacy-team-kashmir",
 "displayName": "Jammu and Kashmir Delegation",
 "roundNumber": 3,
 "kind": "closing-statement",
 "text": "Special Representative, honestly then. We can support the American and British construction: autonomy in the text, a ballot that is not accession-only, screening at every crossing in exchange for camp access. We accept the co-chaired working session and will attend India's bilateral. But New Delhi should hear the price: Article 370 restored and Article 356 rescinded is our floor, not our payment. We will not sign a written renunciation of our people's future to purchase what was taken from us illegitimately in 2019. Our red lines held. Autonomy remains on the ballot because London and Washington held it there. Two were pressed against us. Islamabad demanded we renounce Azad Kashmir and Gilgit-Baltistan as the price of speaking about camps and crossings; we decline, and note who fences whom. Beijing and Moscow would strike autonomy from any ballot entirely — that we will never accept, and an accession-only plebiscite we will boycott, substantially and openly. Unbridged: who administers the investigation. Co-administration by the accused is not neutrality. We propose UNMOGIP-supervised sequencing, dated, and reconvening here within twelve months.",
 "tacticsApplied": [
  "red-line-signaled",
  "coalition-building",
  "deadline-pressure",
  "principled-bargaining-frame"
 ]
}
