{
 "partyTwin": "diplomacy-team-us",
 "displayName": "United States of America",
 "roundNumber": 3,
 "kind": "closing-statement",
 "text": "Special Representative, we were asked for honesty rather than diplomacy. What we support: the screened relief mechanism. China's fund, Russia's vetting, Britain's staffing, India's dated returns programme, Pakistan's insistence that return not be hostage to politics — that is real, and America will help finance and monitor it. Second: India offered to reinstate Article 370, rescind 356 and review AFSPA; the Kashmiri delegation asked for precisely that, with a dated allocation of powers. That is graduated, limited autonomy under another name. Register it, date it, and the United States will back it. Our red lines. The first held — by that route, not by the ballot. The second did not. India, Russia and China each refused an international investigation. New Delhi offers accountability by the accused; we do not accept it, and we will not pretend that gap was bridged. Nor was our working session accepted: Delhi will not sit with Islamabad and Srinagar in one room. Way forward: bank the relief fund, register the Article 370 instrument, keep the investigation alive under UN authority for those who will consent to it, and take nuclear risk and water to a separate track. Washington's channels to both capitals remain open.",
 "tacticsApplied": [
  "principled-bargaining-frame",
  "humanitarian-frame",
  "red-line-signaled",
  "coalition-building"
 ]
}
